pytest_atstack/__init__.py
pytest_atstack/plugin.py
pytest_atstack-0.1.4.dist-info/LICENSE
pytest_atstack-0.1.4.dist-info/METADATA
pytest_atstack-0.1.4.dist-info/WHEEL
pytest_atstack-0.1.4.dist-info/entry_points.txt
pytest_atstack-0.1.4.dist-info/top_level.txt
pytest_atstack-0.1.4.dist-info/RECORD
