Metadata-Version: 2.1
Name: pytest-atstack
Version: 0.1.4
Summary: A simple plugin to use with pytest
Author-email: wuchaochao <chaoc.w@outlook.com>
Maintainer-email: wuchaochao <chaoc.w@outlook.com>
License: 
Project-URL: Repository, https://github.com/chaocwu/pytest-atstack
Classifier: Framework :: Pytest
Classifier: Development Status :: 4 - Beta
Classifier: Intended Audience :: Developers
Classifier: Topic :: Software Development :: Testing
Classifier: Operating System :: OS Independent
Classifier: Programming Language :: Python
Classifier: Programming Language :: Python :: 3.8
Classifier: Programming Language :: Python :: 3.9
Classifier: Programming Language :: Python :: 3.10
Classifier: Programming Language :: Python :: 3.11
Classifier: Programming Language :: Python :: 3.12
Classifier: Programming Language :: Python :: 3 :: Only
Classifier: Programming Language :: Python :: Implementation :: CPython
Classifier: Programming Language :: Python :: Implementation :: PyPy
Classifier: License :: OSI Approved :: MIT License
Requires-Python: >=3.8
License-File: LICENSE
Requires-Dist: pytest>=6.2.0
Requires-Dist: requests>=2.32.3
Requires-Dist: allure-pytest>=2.13.5
